{
  "id": 7,
  "sku": "DIY-GIFT-002",
  "title": "Custom Photo Moon Lamp – 3D Printed Personalized Night Light with LED, Wooden Base, Perfect Gift",
  "category": "Custom Gifts",
  "price": "$42",
  "material": "PLA filament, LED module, wooden base",
  "size": "5.5 inch (14cm) diameter",
  "productionTime": "5-7 days",
  "customization": "图片定制（照片/坐标）",
  "keywords": [
    "photo moon lamp",
    "custom gift",
    "personalized lamp",
    "3D printed lamp"
  ],
  "metaTitle": "Custom Photo Moon Lamp – Personalized 3D Printed LED Gift",
  "metaDescription": "Create your unique Custom Photo Moon Lamp! 3D printed with your photo or coordinates. $42, 5.5-inch, LED & wooden base. Perfect gift. Order now!",
  "shortDescription": "Personalized 3D printed moon lamp with your photo, LED light, and wooden base. Unique gift for any occasion.",
  "fullDescription": "Bring the magic of the moon into your home with our Custom Photo Moon Lamp – a stunning, personalized night light that captures your most cherished memories. Crafted from eco-friendly PLA filament and featuring a warm LED module, this 5.5-inch (14cm) diameter lamp sits on a sleek wooden base, creating a dreamy ambiance in any room.\n\n**How It Works:**\n1. **Upload Your Photo or Coordinates** – Share your favorite image or special location coordinates.\n2. **3D Printing & Assembly** – We meticulously 3D print your design, embed the LED, and mount it on a wooden base.\n3. **Delivery in 5-7 Days** – Your custom lamp is carefully packaged and shipped.\n\n**Why You’ll Love It:**\n- **Sentimental Gift** – Perfect for anniversaries, birthdays, weddings, or just because.\n- **Versatile Decor** – Ideal for bedrooms, living rooms, nurseries, or offices.\n- **Eco-Friendly & Safe** – Made from sustainable PLA filament with a cool-to-touch LED.\n\n**Specifications:**\n- Material: PLA filament, LED module, wooden base\n- Size: 5.5 inches (14 cm) diameter\n- Production Time: 5-7 business days\n- Customization: Upload photo or coordinates\n\nIlluminate your world with a lamp that tells your story. Order your Custom Photo Moon Lamp today and make every night a little more magical!",
  "altTags": [
    "Custom photo moon lamp with LED light on wooden base",
    "Personalized 3D printed moon lamp with uploaded photo",
    "Custom moon night light with coordinates gift"
  ],
  "faq": [
    "How do I upload my photo or coordinates for the lamp?",
    "Is the LED light safe for children or overnight use?",
    "How long does production and shipping typically take?"
  ],
  "generatedAt": "2026-05-17T01:22:09.936Z"
}